licel_alice_api/__init__.py
licel_alice_api/alice_api.py
licel_alice_api/consts.py
licel_alice_api/keycloak_authorized_api.py
licel_alice_api/entities/__init__.py
licel_alice_api/entities/crash_incident_item.py
licel_alice_api/entities/env_check_incident_item.py
licel_alice_api/entities/field_allowed.py
licel_alice_api/entities/incident.py
licel_alice_api/entities/incident_item.py
licel_alice_api/entities/mongo_id.py
licel_alice_api/entities/pkp_incident.py
licel_alice_api/entities/pkp_incident_item.py
licel_alice_api/entities/project.py
licel_alice_api/entities/tamper_incident_item.py
licel_alice_api/params/__init__.py
licel_alice_api/params/list_params.py
licel_alice_api/params/page_params.py
licel_alice_api/params/sort_params.py
licel_alice_api/responses/__init__.py
licel_alice_api/responses/list_response.py
licel_alice_api/responses/status_response.py
licel_alice_api/utils/__init__.py
licel_alice_api/utils/dict_wrapper.py
licel_alice_api-0.1.0.dist-info/METADATA
licel_alice_api-0.1.0.dist-info/WHEEL
licel_alice_api-0.1.0.dist-info/top_level.txt
licel_alice_api-0.1.0.dist-info/RECORD
