Metadata-Version: 2.1
Name: licel-alice-api
Version: 0.1.0
Summary: Alice API
Home-page: UNKNOWN
Author: Licel
License: MIT
Platform: UNKNOWN
Requires-Dist: requests
Requires-Dist: python-keycloak
